[{"signal": "America Sports", "position": "55.5\u00b0W", "satellite": "Intelsat 34", "region": "Americas & Europe", "eirp": "40.3", "frequency": "3885 H", "modulation": "DVB-S2", "feed": "SD"}, {"signal": "Am\u00e9rica Paraguay", "position": "61.0\u00b0W", "satellite": "Amazonas 3", "region": "America", "eirp": "39-40", "frequency": "4195 V", "modulation": "DVB-S2", "feed": "HD"}, {"signal": "Am\u00e9rica TV", "position": "47.5\u00b0W", "satellite": "SES 14", "region": "Europe & America", "eirp": "41", "frequency": "3834 R", "modulation": "DVB-S2", "feed": "HD"}, {"signal": "Aunar", "position": "71.8\u00b0W", "satellite": "Arsat 1", "region": "Argentina", "eirp": "52", "frequency": "11670 V", "modulation": "DVB-S2", "feed": "SD"}, {"signal": "C5N", "position": "71.8\u00b0W", "satellite": "Arsat 1", "region": "Argentina", "eirp": "52", "frequency": "12071 V", "modulation": "DVB-S2", "feed": "HD"}, {"signal": "Canal 10 de Junin", "position": "55.5\u00b0W", "satellite": "Intelsat 34", "region": "Americas & Europe", "eirp": "40.3", "frequency": "3983 H", "modulation": "DVB-S2", "feed": "HD"}, {"signal": "Canal 10 TV R\u00edo Negro", "position": "71.8\u00b0W", "satellite": "Arsat 1", "region": "Argentina", "eirp": "52", "frequency": "12103 H", "modulation": "DVB-S", "feed": "SD"}, {"signal": "Canal 2", "position": "71.8\u00b0W", "satellite": "Arsat 1", "region": "Argentina", "eirp": "52", "frequency": "11590 V", "modulation": "DVB-S2", "feed": "SD"}, {"signal": "Canal 26", "position": "71.8\u00b0W", "satellite": "Arsat 1", "region": "Argentina", "eirp": "52", "frequency": "11590 V", "modulation": "DVB-S2", "feed": "SD"}, {"signal": "Canal de la Ciudad", "position": "71.8\u00b0W", "satellite": "Arsat 1", "region": "Argentina", "eirp": "52", "frequency": "11670 V", "modulation": "DVB-S2", "feed": "SD"}, {"signal": "Canal Luz", "position": "30.0\u00b0W", "satellite": "Hispasat 30W-5", "region": "America", "eirp": "48", "frequency": "12076 V", "modulation": "DVB-S2", "feed": "HD"}, {"signal": "Canal Nueve Santa Cruz", "position": "71.8\u00b0W", "satellite": "Arsat 1", "region": "Argentina", "eirp": "52", "frequency": "11590 V", "modulation": "DVB-S2", "feed": "HD"}, {"signal": "Canal Rural", "position": "55.5\u00b0W", "satellite": "Intelsat 34", "region": "Americas & Europe", "eirp": "40.3", "frequency": "3885 H", "modulation": "DVB-S2", "feed": "SD"}, {"signal": "Chacra TV", "position": "47.5\u00b0W", "satellite": "SES 14", "region": "Europe & America", "eirp": "41", "frequency": "3834 R", "modulation": "DVB-S2", "feed": "HD"}, {"signal": "Cine.ar", "position": "71.8\u00b0W", "satellite": "Arsat 1", "region": "Argentina", "eirp": "52", "frequency": "11590 V", "modulation": "DVB-S2", "feed": "HD"}, {"signal": "CM", "position": "71.8\u00b0W", "satellite": "Arsat 1", "region": "Argentina", "eirp": "52", "frequency": "11640 V", "modulation": "DVB-S2", "feed": "HD"}, {"signal": "CM Internacional", "position": "71.8\u00b0W", "satellite": "Arsat 1", "region": "Argentina", "eirp": "52", "frequency": "11640 V", "modulation": "DVB-S2", "feed": "HD"}, {"signal": "Cr\u00f3nica TV", "position": "71.8\u00b0W", "satellite": "Arsat 1", "region": "Argentina", "eirp": "52", "frequency": "11640 V", "modulation": "DVB-S2", "feed": "HD"}, {"signal": "DeporTV", "position": "71.8\u00b0W", "satellite": "Arsat 1", "region": "Argentina", "eirp": "52", "frequency": "11590 V", "modulation": "DVB-S2", "feed": "HD"}, {"signal": "Doce TV", "position": "71.8\u00b0W", "satellite": "Arsat 1", "region": "Argentina", "eirp": "52", "frequency": "11590 V", "modulation": "DVB-S2", "feed": "SD"}, {"signal": "El Destape TV", "position": "71.8\u00b0W", "satellite": "Arsat 1", "region": "Argentina", "eirp": "52", "frequency": "11590 V", "modulation": "DVB-S2", "feed": "HD"}, {"signal": "El Doce", "position": "71.8\u00b0W", "satellite": "Arsat 1", "region": "Argentina", "eirp": "52", "frequency": "11670 V", "modulation": "DVB-S2", "feed": "SD"}, {"signal": "Extra!", "position": "71.8\u00b0W", "satellite": "Arsat 1", "region": "Argentina", "eirp": "52", "frequency": "11590 V", "modulation": "DVB-S2", "feed": "HD"}, {"signal": "Garage TV", "position": "71.8\u00b0W", "satellite": "Arsat 1", "region": "Argentina", "eirp": "52", "frequency": "11670 V", "modulation": "DVB-S2", "feed": "HD"}, {"signal": "Lapacho Canal 11", "position": "71.8\u00b0W", "satellite": "Arsat 1", "region": "Argentina", "eirp": "52", "frequency": "11590 V", "modulation": "DVB-S2", "feed": "HD"}, {"signal": "LN+", "position": "71.8\u00b0W", "satellite": "Arsat 1", "region": "Argentina", "eirp": "52", "frequency": "12192 V", "modulation": "DVB-S2", "feed": "SD"}, {"signal": "Net TV", "position": "71.8\u00b0W", "satellite": "Arsat 1", "region": "Argentina", "eirp": "52", "frequency": "11670 V", "modulation": "DVB-S2", "feed": "SD"}, {"signal": "Red", "position": "71.8\u00b0W", "satellite": "Arsat 1", "region": "Argentina", "eirp": "52", "frequency": "12131 V", "modulation": "DVB-S2", "feed": "HD"}, {"signal": "RTN", "position": "71.8\u00b0W", "satellite": "Arsat 1", "region": "Argentina", "eirp": "52", "frequency": "12050 V", "modulation": "DVB-S", "feed": "SD"}, {"signal": "San Luis + 2", "position": "71.8\u00b0W", "satellite": "Arsat 1", "region": "Argentina", "eirp": "52", "frequency": "12075 V", "modulation": "DVB-S2", "feed": "HD"}, {"signal": "Somos", "position": "81.0\u00b0W", "satellite": "Arsat 2", "region": "South America", "eirp": "49", "frequency": "11639 H", "modulation": "DVB-S2", "feed": "SD"}, {"signal": "Somos Uno", "position": "71.8\u00b0W", "satellite": "Arsat 1", "region": "Argentina", "eirp": "52", "frequency": "12081 V", "modulation": "DVB-S2", "feed": "HD"}, {"signal": "T5 Satelital", "position": "71.8\u00b0W", "satellite": "Arsat 1", "region": "Argentina", "eirp": "52", "frequency": "11902 V", "modulation": "DVB-S2", "feed": "HD"}, {"signal": "Tec TV", "position": "71.8\u00b0W", "satellite": "Arsat 1", "region": "Argentina", "eirp": "52", "frequency": "11670 V", "modulation": "DVB-S2", "feed": "SD"}, {"signal": "Telefe Neuqu\u00e9n", "position": "71.8\u00b0W", "satellite": "Arsat 1", "region": "Argentina", "eirp": "52", "frequency": "12050 V", "modulation": "DVB-S", "feed": "SD"}, {"signal": "TV Canal 9", "position": "71.8\u00b0W", "satellite": "Arsat 1", "region": "Argentina", "eirp": "52", "frequency": "12187 V", "modulation": "DVB-S", "feed": "SD"}, {"signal": "TV P\u00fablica", "position": "40.5\u00b0W", "satellite": "SES 6", "region": "Hemi", "eirp": "41-42", "frequency": "4071 L", "modulation": "DVB-S2", "feed": "HD"}, {"signal": "TV P\u00fablica Fueguina", "position": "71.8\u00b0W", "satellite": "Arsat 1", "region": "Argentina", "eirp": "52", "frequency": "11590 V", "modulation": "DVB-S2", "feed": "HD"}, {"signal": "TV P\u00fablica Pampeana", "position": "71.8\u00b0W", "satellite": "Arsat 1", "region": "Argentina", "eirp": "52", "frequency": "12097 V", "modulation": "DVB-S2", "feed": "HD"}, {"signal": "TV Santafesina", "position": "71.8\u00b0W", "satellite": "Arsat 1", "region": "Argentina", "eirp": "52", "frequency": "12046 V", "modulation": "DVB-S2", "feed": "HD"}, {"signal": "Unife", "position": "71.8\u00b0W", "satellite": "Arsat 1", "region": "Argentina", "eirp": "52", "frequency": "11670 V", "modulation": "DVB-S2", "feed": "SD"}]